.gitignore
Dockerfile
LICENSE
README.md
requirements.txt
setup.py
assets/continuous_profiling.png
assets/dashboard.png
assets/mocha.png
dashboard/.gitignore
dashboard/README.md
dashboard/package.json
dashboard/tsconfig.json
dashboard/yarn.lock
dashboard/public/favicon.ico
dashboard/public/index.html
dashboard/public/logo192.png
dashboard/public/logo512.png
dashboard/public/manifest.json
dashboard/public/robots.txt
dashboard/src/App.css
dashboard/src/App.tsx
dashboard/src/index.css
dashboard/src/index.tsx
dashboard/src/logo.svg
dashboard/src/react-app-env.d.ts
dashboard/src/reportWebVitals.ts
dashboard/src/setupTests.ts
dashboard/src/assets/mocha.svg
dashboard/src/components/Dashboard.tsx
dashboard/src/components/NavBar.tsx
dashboard/src/components/NavButton.tsx
dashboard/src/components/ProfileChart.tsx
dashboard/src/logic/api.ts
dashboard/src/pages/Home.tsx
mocha/__init__.py
mocha/cache.py
mocha/demo.py
mocha/profiler.py
mocha/state.py
mocha_time.egg-info/PKG-INFO
mocha_time.egg-info/SOURCES.txt
mocha_time.egg-info/dependency_links.txt
mocha_time.egg-info/requires.txt
mocha_time.egg-info/top_level.txt
server/__init__.py
server/config.py
server/main.py
server/requirements.txt
server/start.sh
server/commons/__init__.py
server/commons/database/__init__.py
server/commons/database/sqlite/0.sql
server/commons/database/sqlite/__init__.py
server/commons/logging/__init__.py
server/logic/__init__.py
server/logic/auth.py
server/logic/data.py
server/logic/queries.py